Compiled from "EntityMixin.java"
public abstract class io.github.kosianodangoo.trialmonolith.mixin.EntityMixin extends net.minecraftforge.common.capabilities.CapabilityProvider<net.minecraft.world.entity.Entity> implements net.minecraft.world.Nameable, net.minecraft.world.level.entity.EntityAccess, net.minecraft.commands.CommandSource, net.minecraftforge.common.extensions.IForgeEntity, io.github.kosianodangoo.trialmonolith.api.mixin.ISoulDamage, io.github.kosianodangoo.trialmonolith.api.mixin.ISoulProtection, io.github.kosianodangoo.trialmonolith.api.mixin.ISoulBypass, io.github.kosianodangoo.trialmonolith.api.mixin.IOverClocker, io.github.kosianodangoo.trialmonolith.api.mixin.IHighDimensionalBarrier, io.github.kosianodangoo.trialmonolith.api.mixin.ITickTracker {
  public net.minecraft.network.syncher.SynchedEntityData f_19804_;

  public int f_19797_;

  private static final net.minecraft.network.syncher.EntityDataAccessor<java.lang.Float> the_trial_monolith$DATA_SOUL_DAMAGE_ID;

  private static final net.minecraft.network.syncher.EntityDataAccessor<java.lang.Boolean> the_trial_monolith$DATA_SOUL_PROTECTION_ID;

  private static final net.minecraft.network.syncher.EntityDataAccessor<java.lang.Boolean> the_trial_monolith$DATA_OVER_CLOCKER_ID;

  private static final net.minecraft.network.syncher.EntityDataAccessor<java.lang.Boolean> the_trial_monolith$DATA_HIGH_DIMENSIONAL_BARRIER;

  private boolean the_trial_monolith$isUpdating;

  private boolean the_trial_monolith$shouldBypass;

  private boolean the_trial_monolith$removed;

  private boolean the_trial_monolith$initialized;

  private int the_trial_monolith$lastTickCount;

  protected io.github.kosianodangoo.trialmonolith.mixin.EntityMixin(java.lang.Class<net.minecraft.world.entity.Entity>);
    Code:
       0: aload_0
       1: aload_1
       2: invokespecial #65                 // Method net/minecraftforge/common/capabilities/CapabilityProvider."<init>":(Ljava/lang/Class;)V
       5: aload_0
       6: iconst_0
       7: putfield      #67                 // Field the_trial_monolith$isUpdating:Z
      10: aload_0
      11: iconst_0
      12: putfield      #69                 // Field the_trial_monolith$shouldBypass:Z
      15: aload_0
      16: iconst_0
      17: putfield      #71                 // Field the_trial_monolith$removed:Z
      20: aload_0
      21: iconst_0
      22: putfield      #73                 // Field the_trial_monolith$initialized:Z
      25: aload_0
      26: iconst_0
      27: putfield      #75                 // Field the_trial_monolith$lastTickCount:I
      30: return

  public void onInit(net.minecraft.world.entity.EntityType, net.minecraft.world.level.Level, org.spongepowered.asm.mixin.injection.callback.CallbackInfo);
    Code:
       0: aload_0
       1: getfield      #89                 // Field f_19804_:Lnet/minecraft/network/syncher/SynchedEntityData;
       4: getstatic     #91                 // Field the_trial_monolith$DATA_SOUL_DAMAGE_ID:Lnet/minecraft/network/syncher/EntityDataAccessor;
       7: fconst_0
       8: invokestatic  #97                 // Method java/lang/Float.valueOf:(F)Ljava/lang/Float;
      11: invokevirtual #103                // Method net/minecraft/network/syncher/SynchedEntityData.m_135372_:(Lnet/minecraft/network/syncher/EntityDataAccessor;Ljava/lang/Object;)V
      14: aload_0
      15: getfield      #89                 // Field f_19804_:Lnet/minecraft/network/syncher/SynchedEntityData;
      18: getstatic     #105                // Field the_trial_monolith$DATA_SOUL_PROTECTION_ID:Lnet/minecraft/network/syncher/EntityDataAccessor;
      21: iconst_0
      22: invokestatic  #110                // Method java/lang/Boolean.valueOf:(Z)Ljava/lang/Boolean;
      25: invokevirtual #103                // Method net/minecraft/network/syncher/SynchedEntityData.m_135372_:(Lnet/minecraft/network/syncher/EntityDataAccessor;Ljava/lang/Object;)V
      28: aload_0
      29: getfield      #89                 // Field f_19804_:Lnet/minecraft/network/syncher/SynchedEntityData;
      32: getstatic     #112                // Field the_trial_monolith$DATA_OVER_CLOCKER_ID:Lnet/minecraft/network/syncher/EntityDataAccessor;
      35: iconst_0
      36: invokestatic  #110                // Method java/lang/Boolean.valueOf:(Z)Ljava/lang/Boolean;
      39: invokevirtual #103                // Method net/minecraft/network/syncher/SynchedEntityData.m_135372_:(Lnet/minecraft/network/syncher/EntityDataAccessor;Ljava/lang/Object;)V
      42: aload_0
      43: getfield      #89                 // Field f_19804_:Lnet/minecraft/network/syncher/SynchedEntityData;
      46: getstatic     #114                // Field the_trial_monolith$DATA_HIGH_DIMENSIONAL_BARRIER:Lnet/minecraft/network/syncher/EntityDataAccessor;
      49: iconst_0
      50: invokestatic  #110                // Method java/lang/Boolean.valueOf:(Z)Ljava/lang/Boolean;
      53: invokevirtual #103                // Method net/minecraft/network/syncher/SynchedEntityData.m_135372_:(Lnet/minecraft/network/syncher/EntityDataAccessor;Ljava/lang/Object;)V
      56: aload_0
      57: iconst_1
      58: putfield      #73                 // Field the_trial_monolith$initialized:Z
      61: return

  public boolean the_trial_monolith$isOverClocked();
    Code:
       0: aload_0
       1: getfield      #73                 // Field the_trial_monolith$initialized:Z
       4: ifne          9
       7: iconst_0
       8: ireturn
       9: aload_0
      10: getfield      #89                 // Field f_19804_:Lnet/minecraft/network/syncher/SynchedEntityData;
      13: getstatic     #112                // Field the_trial_monolith$DATA_OVER_CLOCKER_ID:Lnet/minecraft/network/syncher/EntityDataAccessor;
      16: invokevirtual #126                // Method net/minecraft/network/syncher/SynchedEntityData.m_135370_:(Lnet/minecraft/network/syncher/EntityDataAccessor;)Ljava/lang/Object;
      19: checkcast     #107                // class java/lang/Boolean
      22: invokevirtual #129                // Method java/lang/Boolean.booleanValue:()Z
      25: ireturn

  public void the_trial_monolith$setOverClocked(boolean);
    Code:
       0: aload_0
       1: getfield      #73                 // Field the_trial_monolith$initialized:Z
       4: ifne          8
       7: return
       8: aload_0
       9: getfield      #89                 // Field f_19804_:Lnet/minecraft/network/syncher/SynchedEntityData;
      12: getstatic     #112                // Field the_trial_monolith$DATA_OVER_CLOCKER_ID:Lnet/minecraft/network/syncher/EntityDataAccessor;
      15: iload_1
      16: invokestatic  #110                // Method java/lang/Boolean.valueOf:(Z)Ljava/lang/Boolean;
      19: invokevirtual #134                // Method net/minecraft/network/syncher/SynchedEntityData.m_135381_:(Lnet/minecraft/network/syncher/EntityDataAccessor;Ljava/lang/Object;)V
      22: return

  public float the_trial_monolith$getSoulDamage();
    Code:
       0: aload_0
       1: getfield      #73                 // Field the_trial_monolith$initialized:Z
       4: ifne          9
       7: fconst_0
       8: freturn
       9: aload_0
      10: getfield      #89                 // Field f_19804_:Lnet/minecraft/network/syncher/SynchedEntityData;
      13: getstatic     #91                 // Field the_trial_monolith$DATA_SOUL_DAMAGE_ID:Lnet/minecraft/network/syncher/EntityDataAccessor;
      16: invokevirtual #126                // Method net/minecraft/network/syncher/SynchedEntityData.m_135370_:(Lnet/minecraft/network/syncher/EntityDataAccessor;)Ljava/lang/Object;
      19: checkcast     #93                 // class java/lang/Float
      22: invokevirtual #140                // Method java/lang/Float.floatValue:()F
      25: freturn

  public void the_trial_monolith$setSoulDamage(float);
    Code:
       0: aload_0
       1: getfield      #73                 // Field the_trial_monolith$initialized:Z
       4: ifne          8
       7: return
       8: aload_0
       9: getfield      #89                 // Field f_19804_:Lnet/minecraft/network/syncher/SynchedEntityData;
      12: getstatic     #91                 // Field the_trial_monolith$DATA_SOUL_DAMAGE_ID:Lnet/minecraft/network/syncher/EntityDataAccessor;
      15: fload_1
      16: invokestatic  #97                 // Method java/lang/Float.valueOf:(F)Ljava/lang/Float;
      19: invokevirtual #134                // Method net/minecraft/network/syncher/SynchedEntityData.m_135381_:(Lnet/minecraft/network/syncher/EntityDataAccessor;Ljava/lang/Object;)V
      22: return

  public boolean the_trial_monolith$isSoulProtected();
    Code:
       0: aload_0
       1: getfield      #73                 // Field the_trial_monolith$initialized:Z
       4: ifne          9
       7: iconst_0
       8: ireturn
       9: aload_0
      10: getfield      #89                 // Field f_19804_:Lnet/minecraft/network/syncher/SynchedEntityData;
      13: getstatic     #105                // Field the_trial_monolith$DATA_SOUL_PROTECTION_ID:Lnet/minecraft/network/syncher/EntityDataAccessor;
      16: invokevirtual #126                // Method net/minecraft/network/syncher/SynchedEntityData.m_135370_:(Lnet/minecraft/network/syncher/EntityDataAccessor;)Ljava/lang/Object;
      19: checkcast     #107                // class java/lang/Boolean
      22: invokevirtual #129                // Method java/lang/Boolean.booleanValue:()Z
      25: ireturn

  public void the_trial_monolith$setSoulProtected(boolean);
    Code:
       0: aload_0
       1: getfield      #73                 // Field the_trial_monolith$initialized:Z
       4: ifne          8
       7: return
       8: aload_0
       9: getfield      #89                 // Field f_19804_:Lnet/minecraft/network/syncher/SynchedEntityData;
      12: getstatic     #105                // Field the_trial_monolith$DATA_SOUL_PROTECTION_ID:Lnet/minecraft/network/syncher/EntityDataAccessor;
      15: iload_1
      16: invokestatic  #110                // Method java/lang/Boolean.valueOf:(Z)Ljava/lang/Boolean;
      19: invokevirtual #134                // Method net/minecraft/network/syncher/SynchedEntityData.m_135381_:(Lnet/minecraft/network/syncher/EntityDataAccessor;Ljava/lang/Object;)V
      22: return

  public boolean the_trial_monolith$hasHighDimensionalBarrier();
    Code:
       0: aload_0
       1: getfield      #73                 // Field the_trial_monolith$initialized:Z
       4: ifne          9
       7: iconst_0
       8: ireturn
       9: aload_0
      10: getfield      #89                 // Field f_19804_:Lnet/minecraft/network/syncher/SynchedEntityData;
      13: getstatic     #114                // Field the_trial_monolith$DATA_HIGH_DIMENSIONAL_BARRIER:Lnet/minecraft/network/syncher/EntityDataAccessor;
      16: invokevirtual #126                // Method net/minecraft/network/syncher/SynchedEntityData.m_135370_:(Lnet/minecraft/network/syncher/EntityDataAccessor;)Ljava/lang/Object;
      19: checkcast     #107                // class java/lang/Boolean
      22: invokevirtual #129                // Method java/lang/Boolean.booleanValue:()Z
      25: ireturn

  public void the_trial_monolith$setHighDimensionalBarrier(boolean);
    Code:
       0: aload_0
       1: getfield      #73                 // Field the_trial_monolith$initialized:Z
       4: ifne          8
       7: return
       8: aload_0
       9: getfield      #89                 // Field f_19804_:Lnet/minecraft/network/syncher/SynchedEntityData;
      12: getstatic     #114                // Field the_trial_monolith$DATA_HIGH_DIMENSIONAL_BARRIER:Lnet/minecraft/network/syncher/EntityDataAccessor;
      15: iload_1
      16: invokestatic  #110                // Method java/lang/Boolean.valueOf:(Z)Ljava/lang/Boolean;
      19: invokevirtual #134                // Method net/minecraft/network/syncher/SynchedEntityData.m_135381_:(Lnet/minecraft/network/syncher/EntityDataAccessor;Ljava/lang/Object;)V
      22: return

  public int the_trial_monolith$getLastTickCount();
    Code:
       0: aload_0
       1: getfield      #75                 // Field the_trial_monolith$lastTickCount:I
       4: ireturn

  public void the_trial_monolith$updateLastTickCount();
    Code:
       0: aload_0
       1: aload_0
       2: getfield      #155                // Field f_19797_:I
       5: putfield      #75                 // Field the_trial_monolith$lastTickCount:I
       8: return

  public void the_trial_monolith$markUpdating(boolean);
    Code:
       0: aload_0
       1: iload_1
       2: putfield      #67                 // Field the_trial_monolith$isUpdating:Z
       5: return

  public boolean the_trial_monolith$isUpdating();
    Code:
       0: aload_0
       1: getfield      #67                 // Field the_trial_monolith$isUpdating:Z
       4: ireturn

  protected void loadMixin(net.minecraft.nbt.CompoundTag, org.spongepowered.asm.mixin.injection.callback.CallbackInfo);
    Code:
       0: aload_0
       1: aload_1
       2: ldc           #165                // String the_trial_monolith:SoulProtection
       4: invokevirtual #171                // Method net/minecraft/nbt/CompoundTag.m_128471_:(Ljava/lang/String;)Z
       7: invokevirtual #173                // Method the_trial_monolith$setSoulProtected:(Z)V
      10: aload_0
      11: checkcast     #40                 // class net/minecraft/world/entity/Entity
      14: aload_1
      15: ldc           #175                // String the_trial_monolith:SoulDamage
      17: invokevirtual #179                // Method net/minecraft/nbt/CompoundTag.m_128457_:(Ljava/lang/String;)F
      20: invokestatic  #185                // Method io/github/kosianodangoo/trialmonolith/common/helper/EntityHelper.setSoulDamage:(Lnet/minecraft/world/entity/Entity;F)V
      23: aload_0
      24: aload_1
      25: ldc           #187                // String the_trial_monolith:OverClocked
      27: invokevirtual #171                // Method net/minecraft/nbt/CompoundTag.m_128471_:(Ljava/lang/String;)Z
      30: invokevirtual #189                // Method the_trial_monolith$setOverClocked:(Z)V
      33: aload_0
      34: aload_1
      35: ldc           #191                // String the_trial_monolith:HighDimensionalBarrier
      37: invokevirtual #171                // Method net/minecraft/nbt/CompoundTag.m_128471_:(Ljava/lang/String;)Z
      40: invokevirtual #193                // Method the_trial_monolith$setHighDimensionalBarrier:(Z)V
      43: goto          47
      46: astore_3
      47: return
    Exception table:
       from    to  target type
           0    43    46   Class java/lang/Exception

  protected void saveMixin(net.minecraft.nbt.CompoundTag, org.spongepowered.asm.mixin.injection.callback.CallbackInfoReturnable<net.minecraft.nbt.CompoundTag>);
    Code:
       0: aload_1
       1: ldc           #165                // String the_trial_monolith:SoulProtection
       3: aload_0
       4: invokevirtual #201                // Method the_trial_monolith$isSoulProtected:()Z
       7: invokevirtual #205                // Method net/minecraft/nbt/CompoundTag.m_128379_:(Ljava/lang/String;Z)V
      10: aload_1
      11: ldc           #175                // String the_trial_monolith:SoulDamage
      13: aload_0
      14: checkcast     #40                 // class net/minecraft/world/entity/Entity
      17: invokestatic  #209                // Method io/github/kosianodangoo/trialmonolith/common/helper/EntityHelper.getSoulDamage:(Lnet/minecraft/world/entity/Entity;)F
      20: invokevirtual #213                // Method net/minecraft/nbt/CompoundTag.m_128350_:(Ljava/lang/String;F)V
      23: aload_1
      24: ldc           #187                // String the_trial_monolith:OverClocked
      26: aload_0
      27: invokevirtual #215                // Method the_trial_monolith$isOverClocked:()Z
      30: invokevirtual #205                // Method net/minecraft/nbt/CompoundTag.m_128379_:(Ljava/lang/String;Z)V
      33: aload_1
      34: ldc           #191                // String the_trial_monolith:HighDimensionalBarrier
      36: aload_0
      37: invokevirtual #217                // Method the_trial_monolith$hasHighDimensionalBarrier:()Z
      40: invokevirtual #205                // Method net/minecraft/nbt/CompoundTag.m_128379_:(Ljava/lang/String;Z)V
      43: goto          47
      46: astore_3
      47: return
    Exception table:
       from    to  target type
           0    43    46   Class java/lang/Exception

  protected void changeDimensionBeforeMixin(net.minecraft.server.level.ServerLevel, net.minecraftforge.common.util.ITeleporter, org.spongepowered.asm.mixin.injection.callback.CallbackInfoReturnable<net.minecraft.world.entity.Entity>);
    Code:
       0: aload_0
       1: astore        5
       3: aload         5
       5: instanceof    #40                 // class net/minecraft/world/entity/Entity
       8: ifeq          21
      11: aload         5
      13: checkcast     #40                 // class net/minecraft/world/entity/Entity
      16: astore        4
      18: goto          22
      21: return
      22: aload         4
      24: iconst_1
      25: invokestatic  #234                // Method io/github/kosianodangoo/trialmonolith/common/helper/EntityHelper.setBypassProtection:(Lnet/minecraft/world/entity/Entity;Z)V
      28: return

  protected void changeDimensionAfterMixin(net.minecraft.server.level.ServerLevel, net.minecraftforge.common.util.ITeleporter, org.spongepowered.asm.mixin.injection.callback.CallbackInfoReturnable<net.minecraft.world.entity.Entity>);
    Code:
       0: aload_0
       1: astore        5
       3: aload         5
       5: instanceof    #40                 // class net/minecraft/world/entity/Entity
       8: ifeq          21
      11: aload         5
      13: checkcast     #40                 // class net/minecraft/world/entity/Entity
      16: astore        4
      18: goto          22
      21: return
      22: aload         4
      24: iconst_0
      25: invokestatic  #234                // Method io/github/kosianodangoo/trialmonolith/common/helper/EntityHelper.setBypassProtection:(Lnet/minecraft/world/entity/Entity;Z)V
      28: return

  public boolean the_trial_monolith$shouldBypass();
    Code:
       0: aload_0
       1: getfield      #69                 // Field the_trial_monolith$shouldBypass:Z
       4: ifne          14
       7: aload_0
       8: getfield      #71                 // Field the_trial_monolith$removed:Z
      11: ifeq          18
      14: iconst_1
      15: goto          19
      18: iconst_0
      19: ireturn

  public void the_trial_monolith$setShouldBypass(boolean);
    Code:
       0: aload_0
       1: iload_1
       2: putfield      #69                 // Field the_trial_monolith$shouldBypass:Z
       5: return

  public void removeMixin(net.minecraft.world.entity.Entity$RemovalReason, org.spongepowered.asm.mixin.injection.callback.CallbackInfo);
    Code:
       0: aload_0
       1: astore        4
       3: aload         4
       5: instanceof    #40                 // class net/minecraft/world/entity/Entity
       8: ifeq          20
      11: aload         4
      13: checkcast     #40                 // class net/minecraft/world/entity/Entity
      16: astore_3
      17: goto          21
      20: return
      21: aload_3
      22: invokestatic  #254                // Method io/github/kosianodangoo/trialmonolith/common/helper/EntityHelper.shouldBypassProtection:(Lnet/minecraft/world/entity/Entity;)Z
      25: ifeq          34
      28: aload_0
      29: iconst_1
      30: putfield      #71                 // Field the_trial_monolith$removed:Z
      33: return
      34: aload_3
      35: invokestatic  #257                // Method io/github/kosianodangoo/trialmonolith/common/helper/EntityHelper.isSoulProtected:(Lnet/minecraft/world/entity/Entity;)Z
      38: ifeq          52
      41: aload_3
      42: invokestatic  #254                // Method io/github/kosianodangoo/trialmonolith/common/helper/EntityHelper.shouldBypassProtection:(Lnet/minecraft/world/entity/Entity;)Z
      45: ifne          52
      48: aload_2
      49: invokevirtual #262                // Method org/spongepowered/asm/mixin/injection/callback/CallbackInfo.cancel:()V
      52: return

  public void setRemovedMixin(net.minecraft.world.entity.Entity$RemovalReason, org.spongepowered.asm.mixin.injection.callback.CallbackInfo);
    Code:
       0: aload_0
       1: astore        4
       3: aload         4
       5: instanceof    #40                 // class net/minecraft/world/entity/Entity
       8: ifeq          20
      11: aload         4
      13: checkcast     #40                 // class net/minecraft/world/entity/Entity
      16: astore_3
      17: goto          21
      20: return
      21: aload_3
      22: invokestatic  #254                // Method io/github/kosianodangoo/trialmonolith/common/helper/EntityHelper.shouldBypassProtection:(Lnet/minecraft/world/entity/Entity;)Z
      25: ifeq          34
      28: aload_0
      29: iconst_1
      30: putfield      #71                 // Field the_trial_monolith$removed:Z
      33: return
      34: aload_3
      35: invokestatic  #257                // Method io/github/kosianodangoo/trialmonolith/common/helper/EntityHelper.isSoulProtected:(Lnet/minecraft/world/entity/Entity;)Z
      38: ifeq          52
      41: aload_3
      42: invokestatic  #254                // Method io/github/kosianodangoo/trialmonolith/common/helper/EntityHelper.shouldBypassProtection:(Lnet/minecraft/world/entity/Entity;)Z
      45: ifne          52
      48: aload_2
      49: invokevirtual #262                // Method org/spongepowered/asm/mixin/injection/callback/CallbackInfo.cancel:()V
      52: return

  static {};
    Code:
       0: ldc           #40                 // class net/minecraft/world/entity/Entity
       2: getstatic     #273                // Field net/minecraft/network/syncher/EntityDataSerializers.f_135029_:Lnet/minecraft/network/syncher/EntityDataSerializer;
       5: invokestatic  #277                // Method net/minecraft/network/syncher/SynchedEntityData.m_135353_:(Ljava/lang/Class;Lnet/minecraft/network/syncher/EntityDataSerializer;)Lnet/minecraft/network/syncher/EntityDataAccessor;
       8: putstatic     #91                 // Field the_trial_monolith$DATA_SOUL_DAMAGE_ID:Lnet/minecraft/network/syncher/EntityDataAccessor;
      11: ldc           #40                 // class net/minecraft/world/entity/Entity
      13: getstatic     #280                // Field net/minecraft/network/syncher/EntityDataSerializers.f_135035_:Lnet/minecraft/network/syncher/EntityDataSerializer;
      16: invokestatic  #277                // Method net/minecraft/network/syncher/SynchedEntityData.m_135353_:(Ljava/lang/Class;Lnet/minecraft/network/syncher/EntityDataSerializer;)Lnet/minecraft/network/syncher/EntityDataAccessor;
      19: putstatic     #105                // Field the_trial_monolith$DATA_SOUL_PROTECTION_ID:Lnet/minecraft/network/syncher/EntityDataAccessor;
      22: ldc           #40                 // class net/minecraft/world/entity/Entity
      24: getstatic     #280                // Field net/minecraft/network/syncher/EntityDataSerializers.f_135035_:Lnet/minecraft/network/syncher/EntityDataSerializer;
      27: invokestatic  #277                // Method net/minecraft/network/syncher/SynchedEntityData.m_135353_:(Ljava/lang/Class;Lnet/minecraft/network/syncher/EntityDataSerializer;)Lnet/minecraft/network/syncher/EntityDataAccessor;
      30: putstatic     #112                // Field the_trial_monolith$DATA_OVER_CLOCKER_ID:Lnet/minecraft/network/syncher/EntityDataAccessor;
      33: ldc           #40                 // class net/minecraft/world/entity/Entity
      35: getstatic     #280                // Field net/minecraft/network/syncher/EntityDataSerializers.f_135035_:Lnet/minecraft/network/syncher/EntityDataSerializer;
      38: invokestatic  #277                // Method net/minecraft/network/syncher/SynchedEntityData.m_135353_:(Ljava/lang/Class;Lnet/minecraft/network/syncher/EntityDataSerializer;)Lnet/minecraft/network/syncher/EntityDataAccessor;
      41: putstatic     #114                // Field the_trial_monolith$DATA_HIGH_DIMENSIONAL_BARRIER:Lnet/minecraft/network/syncher/EntityDataAccessor;
      44: return
}
