Compiled from "LivingEntityMixin.java"
public abstract class io.github.kosianodangoo.trialmonolith.mixin.LivingEntityMixin extends net.minecraft.world.entity.Entity {
  protected io.github.kosianodangoo.trialmonolith.mixin.LivingEntityMixin(net.minecraft.world.entity.EntityType<? extends net.minecraft.world.entity.LivingEntity>, net.minecraft.world.level.Level);
    Code:
       0: aload_0
       1: aload_1
       2: aload_2
       3: invokespecial #15                 // Method net/minecraft/world/entity/Entity."<init>":(Lnet/minecraft/world/entity/EntityType;Lnet/minecraft/world/level/Level;)V
       6: return

  public void getMaxHealthMixin(org.spongepowered.asm.mixin.injection.callback.CallbackInfoReturnable<java.lang.Float>);
    Code:
       0: aload_0
       1: instanceof    #35                 // class io/github/kosianodangoo/trialmonolith/common/entity/trialmonolith/TrialMonolithEntity
       4: ifeq          20
       7: aload_1
       8: getstatic     #41                 // Field io/github/kosianodangoo/trialmonolith/TrialMonolithConfig.trialMonolithHealth:F
      11: invokestatic  #47                 // Method java/lang/Float.valueOf:(F)Ljava/lang/Float;
      14: invokevirtual #53                 // Method org/spongepowered/asm/mixin/injection/callback/CallbackInfoReturnable.setReturnValue:(Ljava/lang/Object;)V
      17: goto          36
      20: aload_0
      21: instanceof    #55                 // class io/github/kosianodangoo/trialmonolith/common/entity/invadermonolith/InvaderMonolithEntity
      24: ifeq          36
      27: aload_1
      28: ldc           #56                 // float Infinityf
      30: invokestatic  #47                 // Method java/lang/Float.valueOf:(F)Ljava/lang/Float;
      33: invokevirtual #53                 // Method org/spongepowered/asm/mixin/injection/callback/CallbackInfoReturnable.setReturnValue:(Ljava/lang/Object;)V
      36: return

  public void tickDeathMixin(org.spongepowered.asm.mixin.injection.callback.CallbackInfo);
    Code:
       0: aload_0
       1: invokestatic  #68                 // Method io/github/kosianodangoo/trialmonolith/common/helper/EntityHelper.isSoulProtected:(Lnet/minecraft/world/entity/Entity;)Z
       4: ifeq          28
       7: aload_0
       8: invokestatic  #71                 // Method io/github/kosianodangoo/trialmonolith/common/helper/EntityHelper.shouldBypassProtection:(Lnet/minecraft/world/entity/Entity;)Z
      11: ifne          28
      14: aload_0
      15: checkcast     #73                 // class net/minecraft/world/entity/LivingEntity
      18: invokestatic  #79                 // Method io/github/kosianodangoo/trialmonolith/common/helper/MixinMethodHelper.isDeadOrDying:(Lnet/minecraft/world/entity/LivingEntity;)Z
      21: ifeq          28
      24: aload_1
      25: invokevirtual #85                 // Method org/spongepowered/asm/mixin/injection/callback/CallbackInfo.cancel:()V
      28: return
}
